CONTRIBUTORS.txt
LICENSE.txt
MANIFEST.in
Makefile
README.md
changelog.txt
requirements.txt
setup.py
oospectro/__init__.py
oospectro/io.py
oospectro/thickness.py
oospectro.egg-info/PKG-INFO
oospectro.egg-info/SOURCES.txt
oospectro.egg-info/dependency_links.txt
oospectro.egg-info/requires.txt
oospectro.egg-info/top_level.txt