Metadata-Version: 1.2
Name: oospectro
Version: 0.1.1
Summary: A library that calculates thicknesses from ocean optics spectra.
Home-page: https://github.com/sciunto-org/oospectro
Maintainer: F. Boulogne
Maintainer-email: devel@sciunto.org
License: BSD
Platform: all
Provides: oospectro
